README.rst
dorset.py
setup.py
dorset.egg-info/PKG-INFO
dorset.egg-info/SOURCES.txt
dorset.egg-info/dependency_links.txt
dorset.egg-info/requires.txt
dorset.egg-info/top_level.txt