Metadata-Version: 1.1
Name: dorset
Version: 0.4.0
Summary: Package for implementing Dorset remote agent API
Home-page: https://github.com/DorsetProject/dorset-python
Author: Cash Costello
Author-email: cash.costello@gmail.com
License: Apache Software License
Platform: UNKNOWN
Classifier: Development Status :: 4 - Beta
Classifier: Intended Audience :: Developers
Classifier: License :: OSI Approved :: Apache Software License
Classifier: Natural Language :: English
Classifier: Operating System :: OS Independent
Classifier: Programming Language :: Python
Classifier: Programming Language :: Python :: 2.7
Classifier: Programming Language :: Python :: 3
Classifier: Topic :: Internet :: WWW/HTTP
